seqtools/__init__.py
seqtools/buffering.py
seqtools/errors.py
seqtools/evaluation.py
seqtools/indexing.py
seqtools/instrument.py
seqtools/mapping.py
seqtools/serialization.py
seqtools/shape.py
seqtools/utils.py
seqtools/C/__init__.py
seqtools/C/refcountedbuffer.c
seqtools/C/refcountedbuffer.cp312-win_amd64.pyd
seqtools/C/refcountedbuffer.pyi
SeqTools-1.4.1.dist-info/LICENSE.txt
SeqTools-1.4.1.dist-info/METADATA
SeqTools-1.4.1.dist-info/WHEEL
SeqTools-1.4.1.dist-info/top_level.txt
SeqTools-1.4.1.dist-info/RECORD
