Metadata-Version: 2.1
Name: SeqTools
Version: 1.4.1
Summary: A library for transparent transformation of indexable containers (lists, etc.)
Author-email: Nicolas Granger <nicolas.granger.m@gmail.com>
License: Mozilla Public License 2.0 (MPL 2.0)
Project-URL: PyPi, https://pypi.org/project/SeqTools
Project-URL: Documentation, http://seqtools-doc.readthedocs.io
Project-URL: Repository, https://github.com/nlgranger/SeqTools
Keywords: mapping,lazy,delayed,pipeline,processing
Classifier: Programming Language :: Python :: 3
Classifier: Programming Language :: Python :: Implementation :: CPython
Classifier: Operating System :: OS Independent
Classifier: License :: OSI Approved :: Mozilla Public License 2.0 (MPL 2.0)
Classifier: Development Status :: 3 - Alpha
Classifier: Topic :: Software Development :: Libraries :: Python Modules
Classifier: Intended Audience :: Developers
Classifier: Intended Audience :: Science/Research
Requires-Python: >=3.8
License-File: LICENSE.txt
Requires-Dist: tblib
Requires-Dist: threadpoolctl
Provides-Extra: documentation
Requires-Dist: sphinx ; extra == 'documentation'
Requires-Dist: furo ; extra == 'documentation'
Requires-Dist: ipython ; extra == 'documentation'
Requires-Dist: ipykernel ; extra == 'documentation'
Requires-Dist: nbconvert ; extra == 'documentation'
Requires-Dist: nbsphinx ; extra == 'documentation'
Requires-Dist: Pillow ; extra == 'documentation'
Requires-Dist: numpy ; extra == 'documentation'
Provides-Extra: tests
Requires-Dist: pytest ; extra == 'tests'
Requires-Dist: pytest-timeout ; extra == 'tests'
Requires-Dist: numpy ; extra == 'tests'
Requires-Dist: pytest-coverage ; extra == 'tests'
